Himpunan/__init__.py
Himpunan-1.0.1.dist-info/METADATA
Himpunan-1.0.1.dist-info/WHEEL
Himpunan-1.0.1.dist-info/top_level.txt
Himpunan-1.0.1.dist-info/RECORD
