Metadata-Version: 2.1
Name: Himpunan
Version: 1.0.1
Summary: Himpunan dan pemrosesannya
Author: Gilbert Winardy, Hainzel Kemal, Chaiden Foanto
Author-email: gfoucauld@student.ciputra.ac.id
